gtdb/__init__.py
gtdb/async_request.py
gtdb/database.py
gtdb/request.py
gtdb-3.0.0.dist-info/METADATA
gtdb-3.0.0.dist-info/WHEEL
gtdb-3.0.0.dist-info/top_level.txt
gtdb-3.0.0.dist-info/RECORD
