Metadata-Version: 2.1
Name: gtdb
Version: 3.0.0
Summary: It is more convenient to manage a JSON file
Home-page: https://github.com/Dearpixels/gtdb
Author: Asror bek
Author-email: minecraftakk2009beta@gmail.com
Requires-Python: >=3.9
